hatch_bazel_and_pybind11/BUILD.bazel
hatch_bazel_and_pybind11/MODULE.bazel
hatch_bazel_and_pybind11/MODULE.bazel.lock
hatch_bazel_and_pybind11/__about__.py
hatch_bazel_and_pybind11/__init__.py
hatch_bazel_and_pybind11/pybind_extension.so
hatch_bazel_and_pybind11-0.0.5.dist-info/METADATA
hatch_bazel_and_pybind11-0.0.5.dist-info/WHEEL
hatch_bazel_and_pybind11-0.0.5.dist-info/licenses/LICENSE.txt
hatch_bazel_and_pybind11-0.0.5.dist-info/RECORD
