Metadata-Version: 2.3
Name: hatch-bazel-and-pybind11
Version: 0.0.5
Summary: Testing the integration of hatch, bazel and pybind11
Project-URL: Documentation, https://github.com/eguiraud/hatch-bazel-and-pybind11#readme
Project-URL: Issues, https://github.com/eguiraud/hatch-bazel-and-pybind11/issues
Project-URL: Source, https://github.com/eguiraud/hatch-bazel-and-pybind11
Author-email: Enrico Guiraud <enrico.guiraud@pm.me>
License-Expression: MIT
License-File: LICENSE.txt
Classifier: Development Status :: 4 - Beta
Classifier: Operating System :: POSIX :: Linux
Classifier: Programming Language :: Python
Classifier: Programming Language :: Python :: 3.9
Classifier: Programming Language :: Python :: 3.10
Classifier: Programming Language :: Python :: 3.11
Classifier: Programming Language :: Python :: 3.12
Classifier: Programming Language :: Python :: Implementation :: CPython
Requires-Python: >=3.9
